nonebot/adapters/kaiheila/__init__.py
nonebot/adapters/kaiheila/adapter.py
nonebot/adapters/kaiheila/api/__init__.py
nonebot/adapters/kaiheila/api/client.py
nonebot/adapters/kaiheila/api/client.pyi
nonebot/adapters/kaiheila/api/handle.py
nonebot/adapters/kaiheila/api/model.py
nonebot/adapters/kaiheila/bot.py
nonebot/adapters/kaiheila/compat.py
nonebot/adapters/kaiheila/config.py
nonebot/adapters/kaiheila/event.py
nonebot/adapters/kaiheila/exception.py
nonebot/adapters/kaiheila/message.py
nonebot/adapters/kaiheila/permission.py
nonebot/adapters/kaiheila/utils.py
nonebot_adapter_kaiheila-0.3.4.dist-info/LICENSE
nonebot_adapter_kaiheila-0.3.4.dist-info/METADATA
nonebot_adapter_kaiheila-0.3.4.dist-info/WHEEL
nonebot_adapter_kaiheila-0.3.4.dist-info/RECORD
