Metadata-Version: 2.1
Name: nonebot-adapter-kaiheila
Version: 0.3.4
Summary: kaiheila adapter for nonebot2
Home-page: https://github.com/Tian-que/nonebot-adapter-kaiheila
License: MIT
Keywords: bot,khl,kaiheila,khlbot
Author: Tian-que
Author-email: 1605206150@qq.com
Requires-Python: >=3.8,<4.0
Classifier: License :: OSI Approved :: MIT License
Classifier: Programming Language :: Python :: 3
Classifier: Programming Language :: Python :: 3.8
Classifier: Programming Language :: Python :: 3.9
Classifier: Programming Language :: Python :: 3.10
Classifier: Programming Language :: Python :: 3.11
Classifier: Programming Language :: Python :: 3.12
Requires-Dist: nonebot2 (>=2.2.0,<3.0.0)
Requires-Dist: typing-extensions (>=4.8.0,<5.0.0)
Project-URL: Repository, https://github.com/Tian-que/nonebot-adapter-kaiheila
